pyvalidata/__init__.py
pyvalidata/validators.py
pyvalidata-0.1.4.dist-info/LICENSE
pyvalidata-0.1.4.dist-info/METADATA
pyvalidata-0.1.4.dist-info/WHEEL
pyvalidata-0.1.4.dist-info/top_level.txt
pyvalidata-0.1.4.dist-info/RECORD
