Metadata-Version: 2.1
Name: pyvalidata
Version: 0.1.4
Summary: A Python package for data validation
Home-page: https://github.com/EklavyaT/pyvalidata
Author: Eklavya Tomar
Author-email: eklavyaprogramming@gmail.com
License: UNKNOWN
Platform: UNKNOWN
Classifier: License :: OSI Approved :: MIT License
Classifier: Programming Language :: Python :: 3
Classifier: Operating System :: OS Independent
License-File: LICENSE
